json2types/__init__.py
json2types/__main__.py
json2types/cli.py
json2types/generator.py
json2types/py.typed
json2types-0.2.0.dist-info/METADATA
json2types-0.2.0.dist-info/WHEEL
json2types-0.2.0.dist-info/entry_points.txt
json2types-0.2.0.dist-info/RECORD
