Metadata-Version: 2.4
Name: json2types
Version: 0.2.0
Summary: Generate Python TypedDict types from JSON Schema
Requires-Python: >=3.13
Requires-Dist: pydantic==2.11.7
